{
    "check_box": {
        "next": 1642339722,
        "local": "01/16/2022 06:28:42"
    },
    "sheltering": {
        "next": 1642343259,
        "local": "01/16/2022 07:27:39"
    },
    "explore_drag": {
        "next": 1642339468,
        "local": "01/16/2022 06:24:28"
    },
    "sell_quick_box": {
        "next": 1642340926,
        "local": "01/16/2022 06:48:46"
    },
    "trade": {
        "next": 1642339639,
        "local": "01/16/2022 06:27:19"
    },
    "get_vip_box": {
        "next": 1642382399,
        "local": "01/16/2022 18:19:59"
    },
    "training_ground": {
        "next": 1642357802,
        "local": "01/16/2022 11:30:02"
    },
    "get_alli_quest": {
        "next": 1642343522,
        "local": "01/16/2022 07:32:02"
    },
    "get_discount": {
        "next": 1642339543,
        "local": "01/16/2022 06:25:43"
    },
    "train_mil": {
        "next": 1642337899,
        "local": "01/16/2022 05:58:19"
    },
    "daily_msg": {
        "next": 1642355326,
        "local": "01/16/2022 10:48:46"
    },
    "bank_claim": {
        "next": 1642352010,
        "local": "01/16/2022 09:53:30"
    },
    "expeditions": {
        "next": 1642337674,
        "local": "01/16/2022 05:54:34"
    },
    "get_active_award": {
        "next": 1642339502,
        "local": "01/16/2022 06:25:02"
    },
    "auto_transport_rss": {
        "next": 1642339505,
        "local": "01/16/2022 06:25:05"
    },
    "get_alliance_chests": {
        "next": 1642340560,
        "local": "01/16/2022 06:42:40"
    },
    "at_groups": {
        "next": 1642337898,
        "local": "01/16/2022 05:58:18"
    }
}