{
    "check_box": {
        "next": 1645411378,
        "local": "02/20/2022 19:42:58"
    },
    "sheltering": {
        "next": 1645414860,
        "local": "02/20/2022 20:41:00"
    },
    "explore_drag": {
        "next": 1645411687,
        "local": "02/20/2022 19:48:07"
    },
    "sell_quick_box": {
        "next": 1645411617,
        "local": "02/20/2022 19:46:57"
    },
    "trade": {
        "next": 1645411777,
        "local": "02/20/2022 19:49:37"
    },
    "get_vip_box": {
        "next": 1645411909,
        "local": "02/20/2022 19:51:49"
    },
    "training_ground": {
        "next": 1645411998,
        "local": "02/20/2022 19:53:18"
    },
    "get_alli_quest": {
        "next": 1645412059,
        "local": "02/20/2022 19:54:19"
    },
    "get_discount": {
        "next": 1645412344,
        "local": "02/20/2022 19:59:04"
    },
    "train_mil": {
        "next": 1645411429,
        "local": "02/20/2022 19:43:49"
    },
    "daily_msg": {
        "next": 1645411446,
        "local": "02/20/2022 19:44:06"
    },
    "bank_claim": {
        "next": 1645411523,
        "local": "02/20/2022 19:45:23"
    },
    "expeditions": {
        "next": 1645411877,
        "local": "02/20/2022 19:51:17"
    },
    "get_active_award": {
        "next": 1645412031,
        "local": "02/20/2022 19:53:51"
    },
    "auto_transport_rss": {
        "next": 1645412303,
        "local": "02/20/2022 19:58:23"
    },
    "get_alliance_chests": {
        "next": 1645412330,
        "local": "02/20/2022 19:58:50"
    },
    "at_groups": {
        "next": 1645409342,
        "local": "02/20/2022 19:09:02"
    },
    "get_taven": {
        "next": 1645411790,
        "local": "02/20/2022 19:49:50"
    },
    "farm_around": {
        "next": 1645409400,
        "local": "02/20/2022 19:10:00"
    },
    "complete_all_trials": {
        "next": 1645488607,
        "local": "02/21/2022 17:10:07"
    }
}