{
    "check_box": {
        "next": 1645584867,
        "local": "02/22/2022 19:54:27"
    },
    "explore_drag": {
        "next": 1645581526,
        "local": "02/22/2022 18:58:46"
    },
    "sell_quick_box": {
        "next": 1645579168,
        "local": "02/22/2022 18:19:28"
    },
    "trade": {
        "next": 1645584789,
        "local": "02/22/2022 19:53:09"
    },
    "get_vip_box": {
        "next": 1645579199,
        "local": "02/22/2022 18:19:59"
    },
    "training_ground": {
        "next": 1645582570,
        "local": "02/22/2022 19:16:10"
    },
    "get_alli_quest": {
        "next": 1645582677,
        "local": "02/22/2022 19:17:57"
    },
    "get_discount": {
        "next": 1645582831,
        "local": "02/22/2022 19:20:31"
    },
    "train_mil": {
        "next": 1645571074,
        "local": "02/22/2022 16:04:34"
    },
    "daily_msg": {
        "next": 1645609154,
        "local": "02/23/2022 02:39:14"
    },
    "bank_claim": {
        "next": 1646102607,
        "local": "02/28/2022 19:43:27"
    },
    "expeditions": {
        "next": 1645622080,
        "local": "02/23/2022 06:14:40"
    },
    "get_active_award": {
        "next": 1645582649,
        "local": "02/22/2022 19:17:29"
    },
    "auto_transport_rss": {
        "next": 1645582717,
        "local": "02/22/2022 19:18:37"
    },
    "get_alliance_chests": {
        "next": 1645582789,
        "local": "02/22/2022 19:19:49"
    },
    "at_groups": {
        "next": 1645562661,
        "local": "02/22/2022 13:44:21"
    },
    "continue_bub": {
        "next": 1645596549,
        "local": "02/22/2022 23:09:09"
    },
    "get_taven": {
        "next": 1645582267,
        "local": "02/22/2022 19:11:07"
    },
    "upgrade_commanders": {
        "next": 1645563529,
        "local": "02/22/2022 13:58:49"
    },
    "schedule_leader": {
        "next": 1645563041,
        "local": "02/22/2022 13:50:41"
    },
    "farm_around": {
        "next": 1645559811,
        "local": "02/22/2022 12:56:51"
    },
    "complete_all_trials": {
        "next": 1645588678,
        "local": "02/22/2022 20:57:58"
    },
    "rally_camp": {
        "next": 1645563464,
        "local": "02/22/2022 13:57:44"
    }
}