{
    "check_box": {
        "next": 1645075511,
        "local": "02/16/2022 22:25:11"
    },
    "sheltering": {
        "next": 1645085872,
        "local": "02/17/2022 01:17:52"
    },
    "explore_drag": {
        "next": 1645079016,
        "local": "02/16/2022 23:23:36"
    },
    "sell_quick_box": {
        "next": 1645076696,
        "local": "02/16/2022 22:44:56"
    },
    "trade": {
        "next": 1645079174,
        "local": "02/16/2022 23:26:14"
    },
    "get_vip_box": {
        "next": 1645079342,
        "local": "02/16/2022 23:29:02"
    },
    "training_ground": {
        "next": 1645067180,
        "local": "02/16/2022 20:06:20"
    },
    "get_alli_quest": {
        "next": 1645067237,
        "local": "02/16/2022 20:07:17"
    },
    "get_discount": {
        "next": 1645067618,
        "local": "02/16/2022 20:13:38"
    },
    "train_mil": {
        "next": 1645066521,
        "local": "02/16/2022 19:55:21"
    },
    "daily_msg": {
        "next": 1645066537,
        "local": "02/16/2022 19:55:37"
    },
    "bank_claim": {
        "next": 1645066611,
        "local": "02/16/2022 19:56:51"
    },
    "expeditions": {
        "next": 1645079311,
        "local": "02/16/2022 23:28:31"
    },
    "get_active_award": {
        "next": 1645067211,
        "local": "02/16/2022 20:06:51"
    },
    "auto_transport_rss": {
        "next": 1645067462,
        "local": "02/16/2022 20:11:02"
    },
    "get_alliance_chests": {
        "next": 1645067489,
        "local": "02/16/2022 20:11:29"
    },
    "at_groups": {
        "next": 1645067549,
        "local": "02/16/2022 20:12:29"
    },
    "get_taven": {
        "next": 1645079261,
        "local": "02/16/2022 23:27:41"
    },
    "farm_around": {
        "next": 1645067606,
        "local": "02/16/2022 20:13:26"
    },
    "complete_all_trials": {
        "next": 1645078872,
        "local": "02/16/2022 23:21:12"
    }
}