{
    "check_box": {
        "next": 1641624924,
        "local": "01/07/2022 23:55:24"
    },
    "sheltering": {
        "next": 1641630215,
        "local": "01/08/2022 01:23:35"
    },
    "explore_drag": {
        "next": 1641624458,
        "local": "01/07/2022 23:47:38"
    },
    "sell_quick_box": {
        "next": 1641624389,
        "local": "01/07/2022 23:46:29"
    },
    "trade": {
        "next": 1641624548,
        "local": "01/07/2022 23:49:08"
    },
    "get_vip_box": {
        "next": 1641691199,
        "local": "01/08/2022 18:19:59"
    },
    "training_ground": {
        "next": 1641624636,
        "local": "01/07/2022 23:50:36"
    },
    "get_alli_quest": {
        "next": 1641624665,
        "local": "01/07/2022 23:51:05"
    },
    "get_discount": {
        "next": 1641624679,
        "local": "01/07/2022 23:51:19"
    },
    "train_mil": {
        "next": 1641624745,
        "local": "01/07/2022 23:52:25"
    },
    "daily_msg": {
        "next": 1641624761,
        "local": "01/07/2022 23:52:41"
    },
    "bank_claim": {
        "next": 1641624837,
        "local": "01/07/2022 23:53:57"
    }
}