{
    "check_box": {
        "next": 1647743469,
        "local": "03/19/2022 20:31:09"
    },
    "sheltering": {
        "next": 1647747916,
        "local": "03/19/2022 21:45:16"
    },
    "explore_drag": {
        "next": 1647744263,
        "local": "03/19/2022 20:44:23"
    },
    "sell_quick_box": {
        "next": 1647744157,
        "local": "03/19/2022 20:42:37"
    },
    "trade": {
        "next": 1647743244,
        "local": "03/19/2022 20:27:24"
    },
    "get_vip_box": {
        "next": 1647743381,
        "local": "03/19/2022 20:29:41"
    },
    "training_ground": {
        "next": 1647743561,
        "local": "03/19/2022 20:32:41"
    },
    "get_alli_quest": {
        "next": 1647743622,
        "local": "03/19/2022 20:33:42"
    },
    "get_discount": {
        "next": 1647743917,
        "local": "03/19/2022 20:38:37"
    },
    "train_mil": {
        "next": 1647743967,
        "local": "03/19/2022 20:39:27"
    },
    "daily_msg": {
        "next": 1647743985,
        "local": "03/19/2022 20:39:45"
    },
    "bank_claim": {
        "next": 1647744065,
        "local": "03/19/2022 20:41:05"
    },
    "expeditions": {
        "next": 1647743349,
        "local": "03/19/2022 20:29:09"
    },
    "get_active_award": {
        "next": 1647743593,
        "local": "03/19/2022 20:33:13"
    },
    "auto_transport_rss": {
        "next": 1647743875,
        "local": "03/19/2022 20:37:55"
    },
    "get_alliance_chests": {
        "next": 1647743903,
        "local": "03/19/2022 20:38:23"
    },
    "at_groups": {
        "next": 1647742899,
        "local": "03/19/2022 20:21:39"
    },
    "get_taven": {
        "next": 1647743257,
        "local": "03/19/2022 20:27:37"
    },
    "farm_around": {
        "next": 1647742958,
        "local": "03/19/2022 20:22:38"
    },
    "complete_all_trials": {
        "next": 1647744193,
        "local": "03/19/2022 20:43:13"
    }
}