{
    "check_box": {
        "next": 1647279820,
        "local": "03/14/2022 11:43:40"
    },
    "sheltering": {
        "next": 1647282006,
        "local": "03/14/2022 12:20:06"
    },
    "explore_drag": {
        "next": 1647280016,
        "local": "03/14/2022 11:46:56"
    },
    "sell_quick_box": {
        "next": 1647279913,
        "local": "03/14/2022 11:45:13"
    },
    "trade": {
        "next": 1647280104,
        "local": "03/14/2022 11:48:24"
    },
    "get_vip_box": {
        "next": 1647280235,
        "local": "03/14/2022 11:50:35"
    },
    "training_ground": {
        "next": 1647279253,
        "local": "03/14/2022 11:34:13"
    },
    "get_alli_quest": {
        "next": 1647279312,
        "local": "03/14/2022 11:35:12"
    },
    "get_discount": {
        "next": 1647279593,
        "local": "03/14/2022 11:39:53"
    },
    "train_mil": {
        "next": 1647279640,
        "local": "03/14/2022 11:40:40"
    },
    "daily_msg": {
        "next": 1647279657,
        "local": "03/14/2022 11:40:57"
    },
    "bank_claim": {
        "next": 1647279732,
        "local": "03/14/2022 11:42:12"
    },
    "expeditions": {
        "next": 1647280203,
        "local": "03/14/2022 11:50:03"
    },
    "get_active_award": {
        "next": 1647279285,
        "local": "03/14/2022 11:34:45"
    },
    "auto_transport_rss": {
        "next": 1647279552,
        "local": "03/14/2022 11:39:12"
    },
    "get_alliance_chests": {
        "next": 1647279580,
        "local": "03/14/2022 11:39:40"
    },
    "at_groups": {
        "next": 1647276465,
        "local": "03/14/2022 10:47:45"
    },
    "get_taven": {
        "next": 1647280116,
        "local": "03/14/2022 11:48:36"
    },
    "farm_around": {
        "next": 1647276522,
        "local": "03/14/2022 10:48:42"
    },
    "complete_all_trials": {
        "next": 1647279948,
        "local": "03/14/2022 11:45:48"
    }
}