{
    "check_box": {
        "next": 1641420888,
        "local": "01/05/2022 15:14:48"
    },
    "sheltering": {
        "next": 1641424949,
        "local": "01/05/2022 16:22:29"
    },
    "explore_drag": {
        "next": 1641420594,
        "local": "01/05/2022 15:09:54"
    },
    "sell_quick_box": {
        "next": 1641420526,
        "local": "01/05/2022 15:08:46"
    },
    "trade": {
        "next": 1641420682,
        "local": "01/05/2022 15:11:22"
    },
    "get_vip_box": {
        "next": 1641420713,
        "local": "01/05/2022 15:11:53"
    },
    "training_ground": {
        "next": 1641420801,
        "local": "01/05/2022 15:13:21"
    },
    "get_alli_quest": {
        "next": 1641420917,
        "local": "01/05/2022 15:15:17"
    },
    "get_discount": {
        "next": 1641420279,
        "local": "01/05/2022 15:04:39"
    },
    "train_mil": {
        "next": 1641420360,
        "local": "01/05/2022 15:06:00"
    },
    "daily_msg": {
        "next": 1641420312,
        "local": "01/05/2022 15:05:12"
    },
    "bank_claim": {
        "next": 1641420438,
        "local": "01/05/2022 15:07:18"
    }
}