{
    "check_box": {
        "next": 1643456316,
        "local": "01/29/2022 04:38:36"
    },
    "sheltering": {
        "next": 1643462484,
        "local": "01/29/2022 06:21:24"
    },
    "explore_drag": {
        "next": 1643455463,
        "local": "01/29/2022 04:24:23"
    },
    "sell_quick_box": {
        "next": 1643480732,
        "local": "01/29/2022 11:25:32"
    },
    "trade": {
        "next": 1643453535,
        "local": "01/29/2022 03:52:15"
    },
    "get_vip_box": {
        "next": 1643456141,
        "local": "01/29/2022 04:35:41"
    },
    "training_ground": {
        "next": 1643456408,
        "local": "01/29/2022 04:40:08"
    },
    "get_alli_quest": {
        "next": 1643456468,
        "local": "01/29/2022 04:41:08"
    },
    "get_discount": {
        "next": 1643456746,
        "local": "01/29/2022 04:45:46"
    },
    "train_mil": {
        "next": 1643456796,
        "local": "01/29/2022 04:46:36"
    },
    "daily_msg": {
        "next": 1643426193,
        "local": "01/28/2022 20:16:33"
    },
    "bank_claim": {
        "next": 1643425257,
        "local": "01/28/2022 20:00:57"
    },
    "expeditions": {
        "next": 1643456110,
        "local": "01/29/2022 04:35:10"
    },
    "get_active_award": {
        "next": 1643456441,
        "local": "01/29/2022 04:40:41"
    },
    "auto_transport_rss": {
        "next": 1643456703,
        "local": "01/29/2022 04:45:03"
    },
    "get_alliance_chests": {
        "next": 1643456732,
        "local": "01/29/2022 04:45:32"
    },
    "at_groups": {
        "next": 1643425711,
        "local": "01/28/2022 20:08:31"
    },
    "get_taven": {
        "next": 1643456049,
        "local": "01/29/2022 04:34:09"
    }
}