{
    "check_box": {
        "next": 1644453683,
        "local": "02/09/2022 17:41:23"
    },
    "sheltering": {
        "next": 1644464443,
        "local": "02/09/2022 20:40:43"
    },
    "explore_drag": {
        "next": 1644447196,
        "local": "02/09/2022 15:53:16"
    },
    "sell_quick_box": {
        "next": 1644447127,
        "local": "02/09/2022 15:52:07"
    },
    "trade": {
        "next": 1644447284,
        "local": "02/09/2022 15:54:44"
    },
    "get_vip_box": {
        "next": 1644446307,
        "local": "02/09/2022 15:38:27"
    },
    "training_ground": {
        "next": 1644446394,
        "local": "02/09/2022 15:39:54"
    },
    "get_alli_quest": {
        "next": 1644446452,
        "local": "02/09/2022 15:40:52"
    },
    "get_discount": {
        "next": 1644446719,
        "local": "02/09/2022 15:45:19"
    },
    "train_mil": {
        "next": 1644446765,
        "local": "02/09/2022 15:46:05"
    },
    "daily_msg": {
        "next": 1644446781,
        "local": "02/09/2022 15:46:21"
    },
    "bank_claim": {
        "next": 1644447038,
        "local": "02/09/2022 15:50:38"
    },
    "expeditions": {
        "next": 1644446276,
        "local": "02/09/2022 15:37:56"
    },
    "get_active_award": {
        "next": 1644446425,
        "local": "02/09/2022 15:40:25"
    },
    "auto_transport_rss": {
        "next": 1644446679,
        "local": "02/09/2022 15:44:39"
    },
    "get_alliance_chests": {
        "next": 1644446706,
        "local": "02/09/2022 15:45:06"
    },
    "at_groups": {
        "next": 1644446906,
        "local": "02/09/2022 15:48:26"
    },
    "get_taven": {
        "next": 1644447295,
        "local": "02/09/2022 15:54:55"
    },
    "farm_around": {
        "next": 1644446963,
        "local": "02/09/2022 15:49:23"
    }
}