{
    "check_box": {
        "next": 1641349599,
        "local": "01/04/2022 19:26:39"
    },
    "sheltering": {
        "next": 1641354280,
        "local": "01/04/2022 20:44:40"
    },
    "explore_drag": {
        "next": 1641349393,
        "local": "01/04/2022 19:23:13"
    },
    "sell_quick_box": {
        "next": 1641349980,
        "local": "01/04/2022 19:33:00"
    },
    "trade": {
        "next": 1641349483,
        "local": "01/04/2022 19:24:43"
    },
    "get_vip_box": {
        "next": 1641349513,
        "local": "01/04/2022 19:25:13"
    },
    "training_ground": {
        "next": 1641349686,
        "local": "01/04/2022 19:28:06"
    },
    "get_alli_quest": {
        "next": 1641349716,
        "local": "01/04/2022 19:28:36"
    },
    "get_discount": {
        "next": 1641349731,
        "local": "01/04/2022 19:28:51"
    },
    "train_mil": {
        "next": 1641349799,
        "local": "01/04/2022 19:29:59"
    },
    "daily_msg": {
        "next": 1641349816,
        "local": "01/04/2022 19:30:16"
    },
    "bank_claim": {
        "next": 1641349891,
        "local": "01/04/2022 19:31:31"
    }
}