{
    "check_box": {
        "next": 1646355968,
        "local": "03/03/2022 18:06:08"
    },
    "sheltering": {
        "next": 1646365810,
        "local": "03/03/2022 20:50:10"
    },
    "explore_drag": {
        "next": 1646359416,
        "local": "03/03/2022 19:03:36"
    },
    "sell_quick_box": {
        "next": 1646357064,
        "local": "03/03/2022 18:24:24"
    },
    "trade": {
        "next": 1646359569,
        "local": "03/03/2022 19:06:09"
    },
    "get_vip_box": {
        "next": 1646359775,
        "local": "03/03/2022 19:09:35"
    },
    "training_ground": {
        "next": 1646359864,
        "local": "03/03/2022 19:11:04"
    },
    "get_alli_quest": {
        "next": 1646347577,
        "local": "03/03/2022 15:46:17"
    },
    "get_discount": {
        "next": 1646346883,
        "local": "03/03/2022 15:34:43"
    },
    "train_mil": {
        "next": 1646346931,
        "local": "03/03/2022 15:35:31"
    },
    "daily_msg": {
        "next": 1646346947,
        "local": "03/03/2022 15:35:47"
    },
    "bank_claim": {
        "next": 1646347021,
        "local": "03/03/2022 15:37:01"
    },
    "expeditions": {
        "next": 1646359743,
        "local": "03/03/2022 19:09:03"
    },
    "get_active_award": {
        "next": 1646359898,
        "local": "03/03/2022 19:11:38"
    },
    "auto_transport_rss": {
        "next": 1646346756,
        "local": "03/03/2022 15:32:36"
    },
    "get_alliance_chests": {
        "next": 1646346783,
        "local": "03/03/2022 15:33:03"
    },
    "at_groups": {
        "next": 1646347874,
        "local": "03/03/2022 15:51:14"
    },
    "get_taven": {
        "next": 1646359687,
        "local": "03/03/2022 19:08:07"
    },
    "farm_around": {
        "next": 1646348160,
        "local": "03/03/2022 15:56:00"
    },
    "complete_all_trials": {
        "next": 1646359216,
        "local": "03/03/2022 19:00:16"
    }
}