{
    "check_box": {
        "next": 1643679756,
        "local": "01/31/2022 18:42:36"
    },
    "sheltering": {
        "next": 1643687112,
        "local": "01/31/2022 20:45:12"
    },
    "explore_drag": {
        "next": 1643680081,
        "local": "01/31/2022 18:48:01"
    },
    "sell_quick_box": {
        "next": 1643679724,
        "local": "01/31/2022 18:42:04"
    },
    "trade": {
        "next": 1643680204,
        "local": "01/31/2022 18:50:04"
    },
    "get_vip_box": {
        "next": 1643680317,
        "local": "01/31/2022 18:51:57"
    },
    "training_ground": {
        "next": 1643680368,
        "local": "01/31/2022 18:52:48"
    },
    "get_alli_quest": {
        "next": 1643680436,
        "local": "01/31/2022 18:53:56"
    },
    "get_discount": {
        "next": 1643681421,
        "local": "01/31/2022 19:10:21"
    },
    "train_mil": {
        "next": 1643681573,
        "local": "01/31/2022 19:12:53"
    },
    "daily_msg": {
        "next": 1643717612,
        "local": "02/01/2022 05:13:32"
    },
    "bank_claim": {
        "next": 1643681651,
        "local": "01/31/2022 19:14:11"
    },
    "expeditions": {
        "next": 1643680277,
        "local": "01/31/2022 18:51:17"
    },
    "get_active_award": {
        "next": 1643680404,
        "local": "01/31/2022 18:53:24"
    },
    "auto_transport_rss": {
        "next": 1643681356,
        "local": "01/31/2022 19:09:16"
    },
    "get_alliance_chests": {
        "next": 1643681385,
        "local": "01/31/2022 19:09:45"
    },
    "at_groups": {
        "next": 1643682354,
        "local": "01/31/2022 19:25:54"
    },
    "get_taven": {
        "next": 1643680218,
        "local": "01/31/2022 18:50:18"
    }
}