{
    "check_box": {
        "next": 1642591463,
        "local": "01/19/2022 04:24:23"
    },
    "sheltering": {
        "next": 1642598172,
        "local": "01/19/2022 06:16:12"
    },
    "explore_drag": {
        "next": 1642591119,
        "local": "01/19/2022 04:18:39"
    },
    "sell_quick_box": {
        "next": 1642613018,
        "local": "01/19/2022 10:23:38"
    },
    "trade": {
        "next": 1642591209,
        "local": "01/19/2022 04:20:09"
    },
    "get_vip_box": {
        "next": 1642591290,
        "local": "01/19/2022 04:21:30"
    },
    "training_ground": {
        "next": 1642591551,
        "local": "01/19/2022 04:25:51"
    },
    "get_alli_quest": {
        "next": 1642591608,
        "local": "01/19/2022 04:26:48"
    },
    "get_discount": {
        "next": 1642561308,
        "local": "01/18/2022 20:01:48"
    },
    "train_mil": {
        "next": 1642561358,
        "local": "01/18/2022 20:02:38"
    },
    "daily_msg": {
        "next": 1642561377,
        "local": "01/18/2022 20:02:57"
    },
    "bank_claim": {
        "next": 1642561456,
        "local": "01/18/2022 20:04:16"
    },
    "expeditions": {
        "next": 1642591260,
        "local": "01/19/2022 04:21:00"
    },
    "get_active_award": {
        "next": 1642591582,
        "local": "01/19/2022 04:26:22"
    },
    "auto_transport_rss": {
        "next": 1642591836,
        "local": "01/19/2022 04:30:36"
    },
    "get_alliance_chests": {
        "next": 1642561293,
        "local": "01/18/2022 20:01:33"
    },
    "at_groups": {
        "next": 1642561889,
        "local": "01/18/2022 20:11:29"
    }
}