{
    "check_box": {
        "next": 1644596231,
        "local": "02/11/2022 09:17:11"
    },
    "explore_drag": {
        "next": 1644596423,
        "local": "02/11/2022 09:20:23"
    },
    "sell_quick_box": {
        "next": 1644603759,
        "local": "02/11/2022 11:22:39"
    },
    "trade": {
        "next": 1644596280,
        "local": "02/11/2022 09:18:00"
    },
    "get_taven": {
        "next": 1644596851,
        "local": "02/11/2022 09:27:31"
    },
    "get_vip_box": {
        "next": 1644628799,
        "local": "02/11/2022 18:19:59"
    },
    "training_ground": {
        "next": 1644619784,
        "local": "02/11/2022 15:49:44"
    },
    "get_alli_quest": {
        "next": 1644600272,
        "local": "02/11/2022 10:24:32"
    },
    "get_discount": {
        "next": 1644598163,
        "local": "02/11/2022 09:49:23"
    },
    "train_mil": {
        "next": 1644598054,
        "local": "02/11/2022 09:47:34"
    },
    "daily_msg": {
        "next": 1644634495,
        "local": "02/11/2022 19:54:55"
    },
    "bank_claim": {
        "next": 1644731053,
        "local": "02/12/2022 22:44:13"
    },
    "expeditions": {
        "next": 1644596958,
        "local": "02/11/2022 09:29:18"
    },
    "get_active_award": {
        "next": 1644597047,
        "local": "02/11/2022 09:30:47"
    },
    "get_alliance_chests": {
        "next": 1644601674,
        "local": "02/11/2022 10:47:54"
    },
    "at_groups": {
        "next": 1644563614,
        "local": "02/11/2022 00:13:34"
    },
    "auto_transport_rss": {
        "next": 1644597903,
        "local": "02/11/2022 09:45:03"
    },
    "schedule_leader": {
        "next": 1644598803,
        "local": "02/11/2022 10:00:03"
    }
}