{
    "check_box": {
        "next": 1645841089,
        "local": "02/25/2022 19:04:49"
    },
    "sheltering": {
        "next": 1645846884,
        "local": "02/25/2022 20:41:24"
    },
    "explore_drag": {
        "next": 1645841850,
        "local": "02/25/2022 19:17:30"
    },
    "sell_quick_box": {
        "next": 1645841746,
        "local": "02/25/2022 19:15:46"
    },
    "trade": {
        "next": 1645841939,
        "local": "02/25/2022 19:18:59"
    },
    "get_vip_box": {
        "next": 1645840852,
        "local": "02/25/2022 19:00:52"
    },
    "training_ground": {
        "next": 1645840940,
        "local": "02/25/2022 19:02:20"
    },
    "get_alli_quest": {
        "next": 1645841116,
        "local": "02/25/2022 19:05:16"
    },
    "get_discount": {
        "next": 1645841406,
        "local": "02/25/2022 19:10:06"
    },
    "train_mil": {
        "next": 1645841455,
        "local": "02/25/2022 19:10:55"
    },
    "daily_msg": {
        "next": 1645841472,
        "local": "02/25/2022 19:11:12"
    },
    "bank_claim": {
        "next": 1645841548,
        "local": "02/25/2022 19:12:28"
    },
    "expeditions": {
        "next": 1645840821,
        "local": "02/25/2022 19:00:21"
    },
    "get_active_award": {
        "next": 1645840972,
        "local": "02/25/2022 19:02:52"
    },
    "auto_transport_rss": {
        "next": 1645841366,
        "local": "02/25/2022 19:09:26"
    },
    "get_alliance_chests": {
        "next": 1645841393,
        "local": "02/25/2022 19:09:53"
    },
    "at_groups": {
        "next": 1645841598,
        "local": "02/25/2022 19:13:18"
    },
    "get_taven": {
        "next": 1645840766,
        "local": "02/25/2022 18:59:26"
    },
    "farm_around": {
        "next": 1645841657,
        "local": "02/25/2022 19:14:17"
    },
    "complete_all_trials": {
        "next": 1645841780,
        "local": "02/25/2022 19:16:20"
    }
}