{
    "check_box": {
        "next": 1647659664,
        "local": "03/18/2022 21:14:24"
    },
    "explore_drag": {
        "next": 1647658972,
        "local": "03/18/2022 21:02:52"
    },
    "sheltering": {
        "next": 1647661150,
        "local": "03/18/2022 21:39:10"
    },
    "sell_quick_box": {
        "next": 1647658867,
        "local": "03/18/2022 21:01:07"
    },
    "trade": {
        "next": 1647659059,
        "local": "03/18/2022 21:04:19"
    },
    "get_vip_box": {
        "next": 1647659189,
        "local": "03/18/2022 21:06:29"
    },
    "training_ground": {
        "next": 1647659274,
        "local": "03/18/2022 21:07:54"
    },
    "get_alli_quest": {
        "next": 1647659332,
        "local": "03/18/2022 21:08:52"
    },
    "get_discount": {
        "next": 1647658639,
        "local": "03/18/2022 20:57:19"
    },
    "train_mil": {
        "next": 1647658686,
        "local": "03/18/2022 20:58:06"
    },
    "daily_msg": {
        "next": 1647658703,
        "local": "03/18/2022 20:58:23"
    },
    "bank_claim": {
        "next": 1647658779,
        "local": "03/18/2022 20:59:39"
    },
    "expeditions": {
        "next": 1647659158,
        "local": "03/18/2022 21:05:58"
    },
    "get_active_award": {
        "next": 1647659305,
        "local": "03/18/2022 21:08:25"
    },
    "auto_transport_rss": {
        "next": 1647659575,
        "local": "03/18/2022 21:12:55"
    },
    "get_alliance_chests": {
        "next": 1647659827,
        "local": "03/18/2022 21:17:07"
    },
    "at_groups": {
        "next": 1647659741,
        "local": "03/18/2022 21:15:41"
    },
    "get_taven": {
        "next": 1647659070,
        "local": "03/18/2022 21:04:30"
    },
    "farm_around": {
        "next": 1647659801,
        "local": "03/18/2022 21:16:41"
    },
    "complete_all_trials": {
        "next": 1647658902,
        "local": "03/18/2022 21:01:42"
    }
}