{
    "check_box": {
        "next": 1641569326,
        "local": "01/07/2022 08:28:46"
    },
    "sheltering": {
        "next": 1641579695,
        "local": "01/07/2022 11:21:35"
    },
    "explore_drag": {
        "next": 1641572656,
        "local": "01/07/2022 09:24:16"
    },
    "sell_quick_box": {
        "next": 1641570299,
        "local": "01/07/2022 08:44:59"
    },
    "trade": {
        "next": 1641572793,
        "local": "01/07/2022 09:26:33"
    },
    "get_vip_box": {
        "next": 1641572842,
        "local": "01/07/2022 09:27:22"
    },
    "training_ground": {
        "next": 1641572892,
        "local": "01/07/2022 09:28:12"
    },
    "get_alli_quest": {
        "next": 1641572925,
        "local": "01/07/2022 09:28:45"
    },
    "get_discount": {
        "next": 1641572938,
        "local": "01/07/2022 09:28:58"
    },
    "train_mil": {
        "next": 1641560541,
        "local": "01/07/2022 06:02:21"
    },
    "daily_msg": {
        "next": 1641591318,
        "local": "01/07/2022 14:35:18"
    },
    "bank_claim": {
        "next": 1642156603,
        "local": "01/14/2022 03:36:43"
    }
}