{
    "check_box": {
        "next": 1641404993,
        "local": "01/05/2022 10:49:53"
    },
    "sheltering": {
        "next": 1641406889,
        "local": "01/05/2022 11:21:29"
    },
    "explore_drag": {
        "next": 1641405153,
        "local": "01/05/2022 10:52:33"
    },
    "sell_quick_box": {
        "next": 1641405083,
        "local": "01/05/2022 10:51:23"
    },
    "trade": {
        "next": 1641405241,
        "local": "01/05/2022 10:54:01"
    },
    "get_vip_box": {
        "next": 1641405273,
        "local": "01/05/2022 10:54:33"
    },
    "training_ground": {
        "next": 1641405363,
        "local": "01/05/2022 10:56:03"
    },
    "get_alli_quest": {
        "next": 1641405392,
        "local": "01/05/2022 10:56:32"
    },
    "get_discount": {
        "next": 1641405406,
        "local": "01/05/2022 10:56:46"
    },
    "train_mil": {
        "next": 1641405474,
        "local": "01/05/2022 10:57:54"
    },
    "daily_msg": {
        "next": 1641404827,
        "local": "01/05/2022 10:47:07"
    },
    "bank_claim": {
        "next": 1641404905,
        "local": "01/05/2022 10:48:25"
    }
}