{
    "check_box": {
        "next": 1643871132,
        "local": "02/02/2022 23:52:12"
    },
    "sheltering": {
        "next": 1643876207,
        "local": "02/03/2022 01:16:47"
    },
    "explore_drag": {
        "next": 1643871296,
        "local": "02/02/2022 23:54:56"
    },
    "sell_quick_box": {
        "next": 1643871387,
        "local": "02/02/2022 23:56:27"
    },
    "trade": {
        "next": 1643870444,
        "local": "02/02/2022 23:40:44"
    },
    "get_vip_box": {
        "next": 1643870575,
        "local": "02/02/2022 23:42:55"
    },
    "training_ground": {
        "next": 1643870665,
        "local": "02/02/2022 23:44:25"
    },
    "get_alli_quest": {
        "next": 1643870723,
        "local": "02/02/2022 23:45:23"
    },
    "get_discount": {
        "next": 1643870997,
        "local": "02/02/2022 23:49:57"
    },
    "train_mil": {
        "next": 1643871045,
        "local": "02/02/2022 23:50:45"
    },
    "daily_msg": {
        "next": 1643871149,
        "local": "02/02/2022 23:52:29"
    },
    "bank_claim": {
        "next": 1643871227,
        "local": "02/02/2022 23:53:47"
    },
    "expeditions": {
        "next": 1643870543,
        "local": "02/02/2022 23:42:23"
    },
    "get_active_award": {
        "next": 1643870695,
        "local": "02/02/2022 23:44:55"
    },
    "auto_transport_rss": {
        "next": 1643870957,
        "local": "02/02/2022 23:49:17"
    },
    "get_alliance_chests": {
        "next": 1643870983,
        "local": "02/02/2022 23:49:43"
    },
    "at_groups": {
        "next": 1643870194,
        "local": "02/02/2022 23:36:34"
    },
    "get_taven": {
        "next": 1643870455,
        "local": "02/02/2022 23:40:55"
    }
}