{
    "check_box": {
        "next": 1650234239,
        "local": "04/17/2022 16:23:59"
    },
    "sheltering": {
        "next": 1650241749,
        "local": "04/17/2022 18:29:09"
    },
    "explore_drag": {
        "next": 1650234760,
        "local": "04/17/2022 16:32:40"
    },
    "sell_quick_box": {
        "next": 1650235511,
        "local": "04/17/2022 16:45:11"
    },
    "trade": {
        "next": 1650235272,
        "local": "04/17/2022 16:41:12"
    },
    "get_vip_box": {
        "next": 1650234282,
        "local": "04/17/2022 16:24:42"
    },
    "training_ground": {
        "next": 1650235429,
        "local": "04/17/2022 16:43:49"
    },
    "get_alli_quest": {
        "next": 1650234358,
        "local": "04/17/2022 16:25:58"
    },
    "get_discount": {
        "next": 1650235163,
        "local": "04/17/2022 16:39:23"
    },
    "train_mil": {
        "next": 1650179750,
        "local": "04/17/2022 01:15:50"
    },
    "daily_msg": {
        "next": 1650271668,
        "local": "04/18/2022 02:47:48"
    },
    "bank_claim": {
        "next": 1650161374,
        "local": "04/16/2022 20:09:34"
    },
    "expeditions": {
        "next": 1650235374,
        "local": "04/17/2022 16:42:54"
    },
    "get_active_award": {
        "next": 1650234323,
        "local": "04/17/2022 16:25:23"
    },
    "auto_transport_rss": {
        "next": 1650235111,
        "local": "04/17/2022 16:38:31"
    },
    "get_alliance_chests": {
        "next": 1650235144,
        "local": "04/17/2022 16:39:04"
    },
    "at_groups": {
        "next": 1650213087,
        "local": "04/17/2022 10:31:27"
    },
    "get_taven": {
        "next": 1650235318,
        "local": "04/17/2022 16:41:58"
    },
    "complete_all_trials": {
        "next": 1650240606,
        "local": "04/17/2022 18:10:06"
    },
    "upgrade_commanders": {
        "next": 1650234142,
        "local": "04/17/2022 16:22:22"
    },
    "daily_farms": {
        "finished": [
            "mint",
            "quar",
            "lumb",
            "grain",
            "mine"
        ],
        "next": 1650213578,
        "local": "04/17/2022 10:39:38"
    },
    "balanced_farms": {
        "next": 1650148941,
        "local": "04/16/2022 16:42:21"
    }
}