{
    "check_box": {
        "next": 1650038032,
        "local": "04/15/2022 09:53:52"
    },
    "sheltering": {
        "next": 1650046658,
        "local": "04/15/2022 12:17:38"
    },
    "explore_drag": {
        "next": 1650039663,
        "local": "04/15/2022 10:21:03"
    },
    "sell_quick_box": {
        "next": 1650021600,
        "local": "04/15/2022 05:20:00"
    },
    "trade": {
        "next": 1650021396,
        "local": "04/15/2022 05:16:36"
    },
    "get_vip_box": {
        "next": 1650071999,
        "local": "04/15/2022 19:19:59"
    },
    "training_ground": {
        "next": 1650021588,
        "local": "04/15/2022 05:19:48"
    },
    "get_alli_quest": {
        "next": 1650057145,
        "local": "04/15/2022 15:12:25"
    },
    "get_discount": {
        "next": 1650038085,
        "local": "04/15/2022 09:54:45"
    },
    "train_mil": {
        "next": 1650022281,
        "local": "04/15/2022 05:31:21"
    },
    "daily_msg": {
        "next": 1650041600,
        "local": "04/15/2022 10:53:20"
    },
    "bank_claim": {
        "next": 1650261930,
        "local": "04/18/2022 00:05:30"
    },
    "expeditions": {
        "next": 1650021488,
        "local": "04/15/2022 05:18:08"
    },
    "get_active_award": {
        "next": 1650037000,
        "local": "04/15/2022 09:36:40"
    },
    "auto_transport_rss": {
        "next": 1650037934,
        "local": "04/15/2022 09:52:14"
    },
    "get_alliance_chests": {
        "next": 1650038067,
        "local": "04/15/2022 09:54:27"
    },
    "at_groups": {
        "next": 1650024733,
        "local": "04/15/2022 06:12:13"
    },
    "get_taven": {
        "next": 1650021434,
        "local": "04/15/2022 05:17:14"
    },
    "complete_all_trials": {
        "next": 1650067807,
        "local": "04/15/2022 18:10:07"
    },
    "upgrade_commanders": {
        "next": 1650038413,
        "local": "04/15/2022 10:00:13"
    },
    "daily_farms": {
        "finished": [],
        "next": 1650022090,
        "local": "04/15/2022 05:28:10"
    },
    "balanced_farms": {
        "next": 1650022221,
        "local": "04/15/2022 05:30:21"
    }
}